marcgrep/__init__.py
marcgrep/cli.py
marcgrep/color.py
marcgrep/filter.py
marcgrep-1.4.2.dist-info/WHEEL
marcgrep-1.4.2.dist-info/entry_points.txt
marcgrep-1.4.2.dist-info/METADATA
marcgrep-1.4.2.dist-info/RECORD
