Metadata-Version: 2.4
Name: marcgrep
Version: 1.4.2
Summary: search MARC files for regex matches
Keywords: marc,grep,regex,libraries,cli,metadata,bibliographic,cataloging
Author: Eric Phetteplace
Author-email: Eric Phetteplace <phette23@gmail.com>
License-Expression: MIT
Classifier: Development Status :: 5 - Production/Stable
Classifier: Environment :: Console
Classifier: License :: OSI Approved :: MIT License
Classifier: Programming Language :: Python :: 3
Classifier: Operating System :: OS Independent
Classifier: Topic :: Utilities
Requires-Dist: click==8.1.8
Requires-Dist: pymarc==5.3.1
Requires-Dist: termcolor==3.1.0
Requires-Python: >=3.9
Project-URL: homepage, https://github.com/phette23/marcgreppy
Project-URL: issues, https://github.com/phette23/marcgreppy/issues
Project-URL: repository, https://github.com/phette23/marcgreppy
